typediterable/__init__.py
typediterable/core.py
typediterable-0.0.1.dist-info/LICENSE
typediterable-0.0.1.dist-info/METADATA
typediterable-0.0.1.dist-info/WHEEL
typediterable-0.0.1.dist-info/top_level.txt
typediterable-0.0.1.dist-info/RECORD
