Metadata-Version: 2.1
Name: typediterable
Version: 0.0.1
Summary: A Simple python package to apply typing to iterables.
Home-page: https://github.com/osoken/typediterable
Author: osoken
Author-email: osoken.devel@outlook.jp
License: MIT
License-File: LICENSE
Provides-Extra: dev
Requires-Dist: flake8 ; extra == 'dev'
Requires-Dist: pytest ; extra == 'dev'
Requires-Dist: black ; extra == 'dev'
Requires-Dist: mypy ; extra == 'dev'
Requires-Dist: tox ; extra == 'dev'
Requires-Dist: isort ; extra == 'dev'
Requires-Dist: pytest-mock ; extra == 'dev'
Provides-Extra: docs
Requires-Dist: mkdocs ; extra == 'docs'
Requires-Dist: mkdocs-material ; extra == 'docs'
Requires-Dist: mkdocs-include-markdown-plugin ; extra == 'docs'
